src/imshaileshpy/__init__.py'.py
src/imshaileshpy/example.py
src/imshaileshpy/main.py
imshaileshpy-0.0.2.dist-info/LICENSE
imshaileshpy-0.0.2.dist-info/METADATA
imshaileshpy-0.0.2.dist-info/WHEEL
imshaileshpy-0.0.2.dist-info/top_level.txt
imshaileshpy-0.0.2.dist-info/RECORD
